.gbp.conf
.testr.conf
.travis.yml
AUTHORS
ChangeLog
LICENSE
README.md
TESTING.md
doc-requirements.txt
requirements.txt
setup.cfg
setup.py
test-requirements.txt
tox.ini
doc/Makefile
doc/source/conf.py
doc/source/configuration.rst
doc/source/index.rst
doc/source/installation.rst
doc/source/overview.rst
doc/source/requirements.rst
doc/source/test.rst
doc/source/troubleshooting.rst
doc/source/upgrade.rst
doc/source/usage.rst
etc/voms.json
keystone_voms/__init__.py
keystone_voms/core.py
keystone_voms/exception.py
keystone_voms/version.py
keystone_voms/voms.py
keystone_voms.egg-info/PKG-INFO
keystone_voms.egg-info/SOURCES.txt
keystone_voms.egg-info/dependency_links.txt
keystone_voms.egg-info/entry_points.txt
keystone_voms.egg-info/not-zip-safe
keystone_voms.egg-info/pbr.json
keystone_voms.egg-info/requires.txt
keystone_voms.egg-info/top_level.txt
keystone_voms/tests/__init__.py
keystone_voms/tests/fakes.py
keystone_voms/tests/funcional/__init__.py
keystone_voms/tests/funcional/test_middleware_voms_authn.py
keystone_voms/tests/funcional/config_files/keystone_voms.conf
keystone_voms/tests/funcional/config_files/voms.json
keystone_voms/tests/funcional/config_files/voms_multiple_vos.json
keystone_voms/tests/funcional/config_files/voms_no_tenant.json
keystone_voms/tests/funcional/config_files/voms_no_vo.json
keystone_voms/tests/unit/__init__.py
keystone_voms/tests/unit/test_middleware.py
keystone_voms/tests/unit/test_voms.py