Metadata-Version: 1.1
Name: keystone-voms
Version: 10.0.0
Summary: Keystone VOMS module for Keystone.
Home-page: http://ifca.github.io/keystone-voms
Author: Spanish National Research Council (CSIC)
Author-email: aloga@ifca.unican.es
License: Apache-2
Platform: UNKNOWN
Classifier: Development Status :: 5 - Production/Stable
Classifier: Environment :: OpenStack
Classifier: Intended Audience :: Information Technology
Classifier: Intended Audience :: System Administrators
Classifier: License :: OSI Approved :: Apache Software License
Classifier: Operating System :: POSIX :: Linux
Classifier: Programming Language :: Python
Classifier: Programming Language :: Python :: 2
Classifier: Programming Language :: Python :: 2.7
Classifier: Programming Language :: Python :: 2.6
